pablo/__init__.py
pablo/utils.py
pablo/management/__init__.py
pablo/management/commands/__init__.py
pablo/management/commands/pablo.py
django_pablo-0.1.dist-info/METADATA
django_pablo-0.1.dist-info/WHEEL
django_pablo-0.1.dist-info/top_level.txt
django_pablo-0.1.dist-info/RECORD
