Metadata-Version: 2.1
Name: django-pablo
Version: 0.1
Summary: A mediocre django fixture generator
Home-page: https://prdpx7.github.io/
Author: Pradeep Khileri
Author-email: pradeepchoudhary009@gmail.com
License: MIT License
Platform: UNKNOWN
Classifier: Environment :: Web Environment
Classifier: Framework :: Django
Classifier: Framework :: Django :: 2.2
Classifier: Intended Audience :: Developers
Classifier: License :: OSI Approved :: MIT License
Classifier: Operating System :: OS Independent
Classifier: Programming Language :: Python :: 3.6
Classifier: Topic :: Internet :: WWW/HTTP
Classifier: Topic :: Internet :: WWW/HTTP :: Dynamic Content
Requires-Dist: Faker (==6.5.0)
Requires-Dist: Django (>=2.2)
